{"cameraMode":{"drawMode":0,"name":"Shaded","section":"Shading Mode"},"sceneLighting":true,"audioPlay":false,"sceneViewState":{"m_AlwaysRefresh":false,"showFog":true,"showSkybox":true,"showFlares":true,"showImageEffects":true,"showParticleSystems":true,"showVisualEffectGraphs":true,"m_FxEnabled":true},"in2DMode":false,"pivot":{"x":-6.013816833496094,"y":-3.2125606536865236,"z":19.81356430053711},"rotation":{"x":0.21997594833374024,"y":0.74538654088974,"z":-0.2949659526348114,"w":0.5559026598930359},"size":41.82441329956055,"orthographic":false}